{
  "fonts/Gotcha_Gothic_Regular.ttf": "fonts/Gotcha_Gothic_Regular-9c8c4bf74e.ttf",
  "images/_body_bg.jpg": "images/_body_bg-669975904e.jpg",
  "images/body_bg.png": "images/body_bg-24f610d6b5.png",
  "images/facebook.svg": "images/facebook-6477545153.svg",
  "images/favicon.png": "images/favicon-f209d07d2f.png",
  "images/instagram.svg": "images/instagram-894d15dff9.svg",
  "images/location.svg": "images/location-3f28265d89.svg",
  "images/page-hero.jpg": "images/page-hero-471cc88f21.jpg",
  "images/peakmedia-logo.svg": "images/peakmedia-logo-2057c4655d.svg",
  "images/peakmedia_logo_white@2x.png": "images/peakmedia_logo_white@2x-ccdc95a519.png",
  "javascripts/app.js": "javascripts/app-b6ac862fd4bcfbac1d03.js",
  "stylesheets/app.css": "stylesheets/app-d23e785bec.css"
}